hto/__init__.py
hto/_classify.py
hto/_cluster_background.py
hto/_defaults.py
hto/_exceptions.py
hto/_logging.py
hto/_meta.py
hto/_otsu.py
hto/_remove_batch_effect.py
hto/_skew_mixture_model.py
hto/_utils.py
hto/cli.py
hto/data.py
hto/demux.py
hto/denoise.py
hto/dnd.py
hto/external/__init__.py
hto/external/gmm_demux.py
hto/metrics.py
hto/normalise.py
hto/pl/__init__.py
hto/pl/barplot.py
hto/pl/distributions.py
hto/pl/heatmap.py
hto/pl/technical_noise.py
hto/pl/umap.py
hto/pl/umi_gex_hto.py
hto/pl/umiplot.py
hto/report.py
hto/tl/__init__.py
hto/tl/build_background.py
hto-1.1.6.dist-info/LICENSE
hto-1.1.6.dist-info/METADATA
hto-1.1.6.dist-info/WHEEL
hto-1.1.6.dist-info/entry_points.txt
hto-1.1.6.dist-info/RECORD
