Metadata-Version: 2.3
Name: hto
Version: 1.1.6
Summary: A method to demultiplex hashtagged single-cell data.
License: MIT
Keywords: single-cell,demultiplexing,HTO
Author: Tobias Krause
Author-email: krauset@mskcc.org
Requires-Python: >=3.10
Classifier: License :: OSI Approved :: MIT License
Classifier: Operating System :: OS Independent
Classifier: Programming Language :: Python :: 3
Classifier: Programming Language :: Python :: 3.10
Classifier: Programming Language :: Python :: 3.11
Classifier: Programming Language :: Python :: 3.12
Classifier: Programming Language :: Python :: 3.13
Requires-Dist: anndata (>=0.10,<0.13)
Requires-Dist: click (>=8.1)
Requires-Dist: matplotlib (>=3.8,<4)
Requires-Dist: numpy (>=2.0,<3)
Requires-Dist: pandas (>=2.1,<3)
Requires-Dist: pyyaml (>=6)
Requires-Dist: requests (>=2.0,<3)
Requires-Dist: scikit-image (>=0,<1)
Requires-Dist: scikit-learn (>=1.5,<2)
Requires-Dist: scipy (>=1.14,<2)
Requires-Dist: seaborn (>=0.13,<0.14)
Requires-Dist: setuptools (>=65.5.0)
Requires-Dist: tqdm (>=4.0,<5)
Project-URL: Homepage, https://pypi.org/project/hto/
Project-URL: Repository, https://github.com/sail-mskcc/hto_dnd/
